ugrpc_pipe/__init__.py
ugrpc_pipe/ugrpc_pipe_pb2.py
ugrpc_pipe/ugrpc_pipe_pb2_grpc.py
ugrpc_pipe-0.2.4.dist-info/licenses/LICENSE
ugrpc_pipe-0.2.4.dist-info/METADATA
ugrpc_pipe-0.2.4.dist-info/WHEEL
ugrpc_pipe-0.2.4.dist-info/top_level.txt
ugrpc_pipe-0.2.4.dist-info/RECORD
