Metadata-Version: 2.4
Name: ugrpc_pipe
Version: 0.2.4
Summary: protobuf for grpc Pipe
Home-page: https://github.com/ImagineersHub/unity-grpc-build-proto-pipe
Author: esun
Author-email: esun@voteb.com
License: MIT
Keywords: python,grpc
Classifier: Development Status :: 3 - Alpha
Classifier: Programming Language :: Python :: 3.10
License-File: LICENSE
Requires-Dist: grpcio==1.50.0
Requires-Dist: grpcio-tools==1.50.0
Requires-Dist: protobuf<5.0dev,>=4.25.2
Requires-Dist: betterproto[compiler]==2.0.0b5
Dynamic: author
Dynamic: author-email
Dynamic: classifier
Dynamic: description
Dynamic: description-content-type
Dynamic: home-page
Dynamic: keywords
Dynamic: license
Dynamic: license-file
Dynamic: requires-dist
Dynamic: summary
